Metadata-Version: 1.2
Name: Grafico
Version: 0.1.3
Summary: Um pacote para gerar gráficos simples.
Home-page: https://github.com/guilhermedonizetti/Grafico
Author: Guilherme Donizetti
Author-email: guilhermetecnologias@gmail.com
License: MIT
Project-URL: Código fonte, https://github.com/guilhermedonizetti/Grafico
Keywords: gerar gráfico
Platform: UNKNOWN
Classifier: Intended Audience :: Developers
Classifier: License :: OSI Approved :: MIT License
Classifier: Natural Language :: Portuguese (Brazilian)
Classifier: Operating System :: OS Independent
